README.md
setup.py
flask_mysqlcp/__init__.py
flask_mysqlcp.egg-info/PKG-INFO
flask_mysqlcp.egg-info/SOURCES.txt
flask_mysqlcp.egg-info/dependency_links.txt
flask_mysqlcp.egg-info/requires.txt
flask_mysqlcp.egg-info/top_level.txt