Metadata-Version: 2.1
Name: flask-mysqlcp
Version: 1.1.1
Summary: Flask extension to create connection pools with mysqlcp
Home-page: https://github.com/AlaBouali/flask_mysqlcp
Author: AlaBouali
Author-email: trap.leader.123@gmail.com
License: MIT License
Platform: UNKNOWN
Classifier: Programming Language :: Python
Classifier: License :: OSI Approved :: MIT License 
Requires-Python: >=2.7
